cloudrock_client.py
python_cloudrock_client-0.1.7.dist-info/LICENSE.md
python_cloudrock_client-0.1.7.dist-info/METADATA
python_cloudrock_client-0.1.7.dist-info/WHEEL
python_cloudrock_client-0.1.7.dist-info/top_level.txt
python_cloudrock_client-0.1.7.dist-info/RECORD
