Metadata-Version: 2.1
Name: python-cloudrock-client
Version: 0.1.7
Summary: Python API client for backend of Cloudrock project.
Home-page: https://cloudrock.ca
Author: Cloudrock Team
Author-email: Cloudrock <support@cloudrock.ca>
License: MIT
Project-URL: Homepage, https://github.com/kubeworkz/python-cloudrock-client
Project-URL: Bug Tracker, https://github.com/kubeworkz/python-cloudrock-client/issues
Classifier: Programming Language :: Python :: 3
Classifier: License :: OSI Approved :: MIT License
Classifier: Operating System :: OS Independent
Requires-Python: >=3.7
License-File: LICENSE.md
Requires-Dist: requests (>=2.6.0)
